app/__init__.py
app/dummy_worker.py
app/main.py
test/__init__.py
test/setup_test.py
test/test_dispatcher.py
test/test_notification.py
test/test_run_service.py
test/astral_times/__init__.py
test/astral_times/test_astral_time_manager.py
test/astral_times/test_astral_times_config.py
test/astral_times/test_astral_times_publisher.py
test/database/__init__.py
test/database/test_database_utils.py
test/database/test_database_worker.py
test/database/test_integration.py
test/mqtt/__init__.py
test/mqtt/test_mqtt_proxy.py
test/utils/__init__.py
test/utils/test_json_utils.py
test/utils/test_time_utils.py
worker_bunch/__init__.py
worker_bunch/dispatcher.py
worker_bunch/notification.py
worker_bunch/run_service.py
worker_bunch/runner.py
worker_bunch/service_config.py
worker_bunch/service_configurator.py
worker_bunch/service_logging.py
worker_bunch/astral_times/__init__.py
worker_bunch/astral_times/astral_times_config.py
worker_bunch/astral_times/astral_times_manager.py
worker_bunch/astral_times/astral_times_publisher.py
worker_bunch/database/__init__.py
worker_bunch/database/database_config.py
worker_bunch/database/database_connector.py
worker_bunch/database/database_manager.py
worker_bunch/database/database_utils.py
worker_bunch/database/database_worker.py
worker_bunch/mqtt/__init__.py
worker_bunch/mqtt/mqtt_client.py
worker_bunch/mqtt/mqtt_config.py
worker_bunch/mqtt/mqtt_proxy.py
worker_bunch/utils/__init__.py
worker_bunch/utils/json_utils.py
worker_bunch/utils/time_utils.py
worker_bunch/worker/__init__.py
worker_bunch/worker/worker.py
worker_bunch/worker/worker_config.py
worker_bunch/worker/worker_factory.py
worker_bunch-1.0.5.dist-info/LICENSE.txt
worker_bunch-1.0.5.dist-info/METADATA
worker_bunch-1.0.5.dist-info/WHEEL
worker_bunch-1.0.5.dist-info/top_level.txt
worker_bunch-1.0.5.dist-info/RECORD
