Metadata-Version: 2.1
Name: worker-bunch
Version: 1.0.5
Summary: Task/job/rule engine, primarily intended for use in a smarthome environment.
Home-page: https://github.com/rosenloecher-it/worker-bunch
Author: Rosenloecher-IT (Raul Rosenlöcher)
Author-email: <github@rosenloecher-it.de>
License: UNKNOWN
Keywords: smarthome,mqtt,rule-engine,task-engine
Platform: UNKNOWN
Classifier: Development Status :: 5 - Production/Stable
Classifier: Environment :: Console
Classifier: Intended Audience :: Developers
Classifier: Operating System :: POSIX :: Linux
Classifier: Programming Language :: Python :: 3
Classifier: License :: OSI Approved :: MIT License
License-File: LICENSE.txt
Requires-Dist: astral ==2.2
Requires-Dist: attrs ==23.1.0
Requires-Dist: click ==8.1.7
Requires-Dist: jsonschema ==4.19.0
Requires-Dist: paho-mqtt ==1.6.1
Requires-Dist: psycopg ==3.1.10
Requires-Dist: pycron ==3.0.0
Requires-Dist: pyyaml ==6.0.1
Requires-Dist: rx ==3.2.0
Requires-Dist: schedule ==1.2.0
Requires-Dist: tzlocal ==5.0.1
